koin/__init__.py
koin/koin.py
koin-0.0.3.dist-info/LICENSE
koin-0.0.3.dist-info/METADATA
koin-0.0.3.dist-info/WHEEL
koin-0.0.3.dist-info/top_level.txt
koin-0.0.3.dist-info/RECORD
