Metadata-Version: 2.1
Name: koin
Version: 0.0.3
Summary: A simple library for Coinbase Pro
Home-page: https://github.com/ernestomonroy/koin
Author: Ernesto Monroy
License: UNKNOWN
Project-URL: Bug Reports, https://github.com/ernestomonroy/koin/issues
Project-URL: Source, https://github.com/ernestomonroy/koin
Keywords: meli
Platform: UNKNOWN
Classifier: Development Status :: 3 - Alpha
Classifier: Intended Audience :: Developers
Classifier: Topic :: Utilities
Classifier: License :: OSI Approved :: MIT License
Classifier: Programming Language :: Python :: 3
Requires-Python: >=3.5
License-File: LICENSE
